kanmanipriya_ml_lab/__init__.py
kanmanipriya_ml_lab/ex1.py
kanmanipriya_ml_lab-0.1.dist-info/METADATA
kanmanipriya_ml_lab-0.1.dist-info/WHEEL
kanmanipriya_ml_lab-0.1.dist-info/top_level.txt
kanmanipriya_ml_lab-0.1.dist-info/RECORD
