Metadata-Version: 2.4
Name: kanmanipriya_ml_lab
Version: 0.1
Summary: ML Lab Exercises Package
Author: pradhanya
Requires-Python: >=3.6
Requires-Dist: scikit-learn
Dynamic: author
Dynamic: requires-dist
Dynamic: requires-python
Dynamic: summary
